{"users": {"1": {"user_id": 1, "email": "megan@email.com", "first_name": "Megan", "last_name": "Bass", "password": "1234", "is_admin": false}}, "calendar_entries": {"1": {"entry_id": 1, "user_id": 1, "entry_date": "2026-02-04", "entry_type": "both"}}, "gambling": {"1": {"user_id": 1, "entry_id": 1, "amount_spent": 100, "amount_earned": 20, "time_spent": "2 hours", "gambling_type": "slots", "emotion_before": "stressed", "emotion_during": "excited", "emotion_after": "regret"}}, "alcohol": {"1": {"user_id": 1, "entry_id": 1, "money_spent": 30, "num_drinks": 4, "trigger": "friends"}}}